packagebmi/__init__.py
packagebmi/filebmi.py
packagebmi-0.0.1.dist-info/LICENSE.txt
packagebmi-0.0.1.dist-info/METADATA
packagebmi-0.0.1.dist-info/WHEEL
packagebmi-0.0.1.dist-info/top_level.txt
packagebmi-0.0.1.dist-info/RECORD
