Metadata-Version: 2.1
Name: packagebmi
Version: 0.0.1
Summary: Package for individual Body Mass Index.
Home-page: https://github.com/glaucomori/packagebmi
Author: Glauco Issamu Pereira Mori
Author-email: glauco.mori@outlook.com
Requires-Python: >=3.8
License-File: LICENSE.txt
